{"error":null,"hits":10000,"facets":{},"content":{"sidebar":{},"search_results":{}},"jobs":[{"basic_qualifications":"- 1+ years of sales experience\u003cbr/\u003e- Bachelor's degree","business_category":"seller-services","city":"Gurugram","company_name":"ASSPL - Haryana","country_code":"IND","description":"Senior Associate-Account Management(Level 3)\u003cbr/\u003e \u003cbr/\u003e  \u003cbr/\u003eJob summary\u003cbr/\u003eAmazon is seeking to hire a Strategic Account Manager in our team to help build our key categories by managing our top and most strategic Selling Partner Accounts. You will join a high performing, learning-oriented, analytical team, who are motivated to work hard, have fun, and make history\u003cbr/\u003e\u003cbr/\u003eAs a Strategic Account Manager, you will be owning relationships with our most Strategic partners and driving them to improve their customer experience and Amazon strategy. Responsibilities include expanding our product selection, improving product availability, building and maintaining strong relationships with key partners (both internally and externally), category analytics and driving overall improvements to the Amazon store.\u003cbr/\u003e\u003cbr/\u003eSo what is involved in this role day-to-day? It’s incredibly varied, so you need to enjoy managing multiple projects and problem-solving! You’ll also be working to:\u003cbr/\u003e\u003cbr/\u003e· Managing the seller relationship by championing the seller’s needs at Amazon. Build strong communication channels at all levels of the seller’s organization, set proper expectations, provide clear status communications, and manage towards a growth plan.\u003cbr/\u003e· Work closely with Leadership on planning and business strategy for Consumables, completing in-depth analysis into customer trends\u003cbr/\u003e· Analyze industry and Amazon internal data to understand competitive landscape across multiple categories and identify customer trends\u003cbr/\u003e· Conduct financial analysis of business opportunities to meet and exceed revenue and profitability targets\u003cbr/\u003e· Managing and driving the growth of the seller’s business: Build and execute on a strategic account plan that delivers on key business opportunities for the seller and Amazon.\u003cbr/\u003e· Managing key improvement initiatives and projects: Drive new product launches and relationship extensions by partnering with the business development and onboarding teams.\u003cbr/\u003e· Work with sellers to improve operational aspects of their business in providing a great consumer experience.\u003cbr/\u003e· Analyzing the business: Conduct deep dive analysis and provide routine executive-level reporting on the seller’s current business and future opportunities. Publish recommendations and action plans based on data.\u003cbr/\u003e· Providing thought leadership around planning, roadmaps and execution\u003cbr/\u003e\u003cbr/\u003e\u003cbr/\u003e\u003cbr/\u003eKey job responsibilities\u003cbr/\u003eSo what is involved in this role day-to-day? It’s incredibly varied, so you need to enjoy managing multiple projects and problem-solving! You’ll also be working to:\u003cbr/\u003e\u003cbr/\u003e· Managing the seller relationship by championing the seller’s needs at Amazon. Build strong communication channels at all levels of the seller’s organization, set proper expectations, provide clear status communications, and manage towards a growth plan.\u003cbr/\u003e· Work closely with Leadership on planning and business strategy for Consumables, completing in-depth analysis into customer trends\u003cbr/\u003e· Analyze industry and Amazon internal data to understand competitive landscape across multiple categories and identify customer trends\u003cbr/\u003e· Conduct financial analysis of business opportunities to meet and exceed revenue and profitability targets\u003cbr/\u003e· Managing and driving the growth of the seller’s business: Build and execute on a strategic account plan that delivers on key business opportunities for the seller and Amazon.\u003cbr/\u003e· Managing key improvement initiatives and projects: Drive new product launches and relationship extensions by partnering with the business development and onboarding teams.\u003cbr/\u003e· Work with sellers to improve operational aspects of their business in providing a great consumer experience.\u003cbr/\u003e· Analyzing the business: Conduct deep dive analysis and provide routine executive-level reporting on the seller’s current business and future opportunities. Publish recommendations and action plans based on data.\u003cbr/\u003e· Providing thought leadership around planning, roadmaps and execution\u003cbr/\u003e\u003cbr/\u003eBASIC QUALIFICATIONS\u003cbr/\u003e3+ years of sales experience\u003cbr/\u003eExperience analyzing data and best practices to assess performance drivers\u003cbr/\u003e\u003cbr/\u003ePREFERRED QUALIFICATIONS:\u003cbr/\u003eMBA degree\u003cbr/\u003eEcomm experience","department_cost_center":null,"description_short":"Senior Associate-Account Management(Level 3)   Job summaryAmazon is seeking to hire a Strategic Account Manager in our team to help build our key categories by managing our top and most strategic Selling","display_distance":null,"id":"489c3b5a-6135-48c3-bbac-53da64a74740","id_icims":"10388305","is_intern":null,"is_manager":null,"job_category":"Sales, Advertising, \u0026 Account Management","job_family":"Sales/account Management","job_function_id":null,"job_path":"/en/jobs/10388305/senior-associate-account-management-uam","job_schedule_type":"full-time","location":"IN, HR, Gurugram","locations":["{\"normalizedStateName\":\"Haryana\",\"normalizedCountryCode\":\"IND\",\"city\":\"Gurugram\",\"countryIso3a\":\"IND\",\"countryIso2a\":\"IN\",\"locationNonStemming\":\"India, HR, Gurugram\",\"coordinates\":\"28.47716,77.06847\",\"normalizedCountyName\":\"Gurugram\",\"type\":\"ONSITE\",\"normalizedCountryName\":\"India\",\"normalizedLocation\":\"Gurugram, Haryana, IND\",\"location\":\"IN, HR, Gurugram\",\"region\":\"HR\",\"buildingCodeList\":[\"HDX1\",\"SDEG\",\"TSE1\",\"SHDZ\",\"TSE7\",\"PNGX\",\"PHSJ\",\"DEL19\",\"PDLV\",\"PHSC\",\"IRDH\",\"UHSE\",\"FDL9\",\"HBX1\",\"DEL73\",\"PHSI\",\"KELH\",\"TSH3\",\"SDEW\",\"HHS5\",\"DEL8\",\"SDEY\",\"DEL94\",\"UHSI\",\"SDEB\",\"HNDJ\",\"TSB3\",\"QNZZ\",\"SDLD\",\"PDLG\",\"SDEP\",\"HDLC\",\"KSZ2\",\"HNDI\",\"DEL24\",\"DED4\",\"HDO2\",\"HHS7\",\"UDEV\",\"KNDA\",\"UHSD\",\"PNGZ\",\"HDO3\",\"FDL6\",\"DED5\",\"PHSE\",\"UHSJ\",\"ZNJS\",\"YZZ4\",\"HHS6\",\"TDK9\",\"XNAB\"],\"normalizedCityName\":\"Gurugram\"}"],"normalized_location":"Gurugram, Haryana, IND","optional_search_labels":[],"posted_date":"April 10, 2026","preferred_qualifications":"- 2+ years of sales experience\u003cbr/\u003e\u003cbr/\u003eOur inclusive culture empowers Amazonians to deliver the best results for our customers. If you have a disability and need a workplace accommodation or adjustment during the application and hiring process, including support for the interview or onboarding process, please visit \u003ca href=\"https://amazon.jobs/content/en/how-we-hire/accommodations\"\u003ehttps://amazon.jobs/content/en/how-we-hire/accommodations\u003c/a\u003e for more information. If the country/region you’re applying in isn’t listed, please contact your Recruiting Partner.","primary_search_label":"seller-services.no-team-listed","source_system":"JobCreator","state":"HR","title":"Senior Associate - Account Management, UAM","university_job":null,"updated_time":"3 minutes","url_next_step":"https://account.amazon.com/jobs/10388305/apply","team":{"id":null,"business_category_id":null,"identifier":null,"label":"no-team-listed","created_at":null,"updated_at":null,"image_file_name":null,"image_content_type":null,"image_file_size":null,"image_updated_at":null,"thumbnail_file_name":null,"thumbnail_content_type":null,"thumbnail_file_size":null,"thumbnail_updated_at":null,"hide_jobs":null,"title":null,"headline":null,"description":null}},{"basic_qualifications":"- 2+ years of non-internship professional software development experience\u003cbr/\u003e- Experience programming with at least one software programming language\u003cbr/\u003e- Knowledge of professional software engineering \u0026 best practices for full software development life cycle, including coding standards, software architectures, code reviews, source control management, continuous deployments, testing, and operational excellence\u003cbr/\u003e- Experience contributing to the architecture and design (architecture, design patterns, reliability and scaling) of new and current systems","business_category":"international-stores","city":"Bengaluru","company_name":"ADCI - Karnataka","country_code":"IND","description":"Want to be part of a dynamic start-up environment within Amazon and be at the forefront of enabling \"Amazon Pay\" outside of Amazon?\u003cbr/\u003eOur team is looking for passionate, experienced software developer who can deliver high quality platform solutions  to support our customers (buyers and merchants) enabling \"Amazon Pay\" to scale as the universal wallet for all of Amazon buyers. \u003cbr/\u003e\u003cbr/\u003eAs an engineer in Amazon Pay, you will be part of a dynamic team working on complex problems innovating on behalf of our customers. As an SDE II, you will play a key role in building a world-class, frictionless payments solution and merchant experience that helps us scale while retaining customer and merchant trust.\u003cbr/\u003e\u003cbr/\u003eThis is an excellent opportunity to join Amazon's world-class technology teams, working alongside some of the industry's top engineers. You will have access to mentoring programs, regular tech talks with principal engineers, and opportunities to develop your skills and advance your career within one of the most innovative and progressive technology companies.\u003cbr/\u003e\u003cbr/\u003eIf you're passionate about building transformative payment solutions that enable merchants and delight customers, we encourage you to apply.   \u003cbr/\u003e\u003cbr/\u003eCome join us as we work hard, have Fun and make History!\u003cbr/\u003e  \u003cbr/\u003e\u003cbr/\u003eKey job responsibilities\u003cbr/\u003e- Deliver high-quality platform solutions supporting diverse customer and merchant use cases for Amazon Pay\u003cbr/\u003e- Develop and enhance web-based applications and web services that enable third-party merchants to integrate Amazon Pay\u003cbr/\u003e- Design and build large-scale, distributed systems to handle high-volume transactions in a 24/7 environment\u003cbr/\u003e- Contribute to the architecture, design, and evolution of new and existing systems focusing on reliability, scalability, and performance\u003cbr/\u003e\u003cbr/\u003eAbout the team\u003cbr/\u003eAmazonPay, one of the fastest growing businesses of Amazon, enables e-commerce websites to accept, and customers to utilise the payment information stored in their Amazon.com accounts to pay for goods and services at sites off-Amazon. AmazonPay also enables customers to manage their account preferences and see their off-Amazon transactions.   Hundreds of thousands of Users make millions of transactions worldwide on AmazonPay. We develop software at every level of the stack from front-end user interfaces to backend server software and everything in between.","department_cost_center":null,"description_short":"Want to be part of a dynamic start-up environment within Amazon and be at the forefront of enabling \"Amazon Pay\" outside of Amazon?Our team is looking for passionate, experienced software developer who","display_distance":null,"id":"0588e4e5-b757-49af-8fce-ae87d37a887c","id_icims":"3202055","is_intern":null,"is_manager":null,"job_category":"Software Development","job_family":"Software Development","job_function_id":null,"job_path":"/en/jobs/3202055/software-development-engineer-ii-amazon-pay","job_schedule_type":"full-time","location":"IN, KA, Bengaluru","locations":["{\"normalizedStateName\":\"Karnataka\",\"normalizedCountryCode\":\"IND\",\"city\":\"Bengaluru\",\"countryIso3a\":\"IND\",\"countryIso2a\":\"IN\",\"locationNonStemming\":\"India, KA, Bengaluru\",\"coordinates\":\"12.96617,77.58692\",\"normalizedCountyName\":\"Bengaluru\",\"type\":\"ONSITE\",\"normalizedCountryName\":\"India\",\"normalizedLocation\":\"Bengaluru, Karnataka, IND\",\"location\":\"IN, KA, Bengaluru\",\"region\":\"KA\",\"buildingCodeList\":[\"BLR26\"],\"normalizedCityName\":\"Bengaluru\"}","{\"normalizedStateName\":\"Telangana\",\"normalizedCountryCode\":\"IND\",\"city\":\"Hyderabad\",\"countryIso3a\":\"IND\",\"countryIso2a\":\"IN\",\"locationNonStemming\":\"India, Hyderabad\",\"coordinates\":\"17.3949,78.47081\",\"normalizedCountyName\":\"Hyderabad\",\"type\":\"ONSITE\",\"normalizedCountryName\":\"India\",\"normalizedLocation\":\"Hyderabad, Telangana, IND\",\"location\":\"IN, Hyderabad\",\"region\":\"\",\"buildingCodeList\":[\"YSO4\"],\"normalizedCityName\":\"Hyderabad\"}"],"normalized_location":"Bengaluru, Karnataka, IND","optional_search_labels":[],"posted_date":"March 11, 2026","preferred_qualifications":"- Bachelor's degree in computer science or equivalent\u003cbr/\u003e- Experience building complex software systems that have been successfully delivered to customers\u003cbr/\u003e- Experience programming with at least one modern language such as Java, C++, or C# including object-oriented design\u003cbr/\u003e\u003cbr/\u003eOur inclusive culture empowers Amazonians to deliver the best results for our customers. If you have a disability and need a workplace accommodation or adjustment during the application and hiring process, including support for the interview or onboarding process, please visit \u003ca href=\"https://amazon.jobs/content/en/how-we-hire/accommodations\"\u003ehttps://amazon.jobs/content/en/how-we-hire/accommodations\u003c/a\u003e for more information. If the country/region you’re applying in isn’t listed, please contact your Recruiting Partner.","primary_search_label":"international-stores.team-amazon-payments","source_system":"JobCreator","state":"KA","title":"Software Development Engineer II , Amazon Pay","university_job":null,"updated_time":"5 minutes","url_next_step":"https://account.amazon.com/jobs/3202055/apply","team":{"id":null,"business_category_id":null,"identifier":null,"label":"team-amazon-payments","created_at":null,"updated_at":null,"image_file_name":null,"image_content_type":null,"image_file_size":null,"image_updated_at":null,"thumbnail_file_name":null,"thumbnail_content_type":null,"thumbnail_file_size":null,"thumbnail_updated_at":null,"hide_jobs":null,"title":null,"headline":null,"description":null}},{"basic_qualifications":"- 2+ years of software development, or 2+ years of technical support experience\u003cbr/\u003e- Experience scripting in modern program languages\u003cbr/\u003e- Experience troubleshooting and debugging technical systems\u003cbr/\u003e- Bachelor's degree or equivalent","business_category":"ecp","city":"Bengaluru","company_name":"ADCI - Karnataka","country_code":"IND","description":"The Hosted Execution (HEX) team is looking for a DevOps Engineer to join and deliver strategic goals for Amazon Global Infrastructure Runtime for Developers (GRID) systems. This is a contract position and is a great opportunity to join our team and manage/build tech solutions that empower our customers. You will be responsible for customer support, migrations, troubleshooting, maintenance, customer engagement and identifying opportunities for automation to improve the developer productivity. If you feel excited by the challenge of setting the course for large company wide initiatives, supporting and managing customer facing products across amazon, this may be the next big career move for you. The ideal candidate must be detail oriented, have good verbal and written communication skills, organizational skills, able to juggle multiple tasks at once, able to work independently and can maintain professionalism under pressure. You must be able to identify problems before they happen and implement solutions that detect and prevent outages. You must be able to accurately prioritize projects, make sound judgments, work to improve the customer experience, and get the right things done.\u003cbr/\u003e\u003cbr/\u003e","department_cost_center":null,"description_short":"The Hosted Execution (HEX) team is looking for a DevOps Engineer to join and deliver strategic goals for Amazon Global Infrastructure Runtime for Developers (GRID) systems. This is a contract position","display_distance":null,"id":"81446848-8719-488a-9d37-6413c3036c3e","id_icims":"3154884","is_intern":null,"is_manager":null,"job_category":"Operations, IT, \u0026 Support Engineering","job_family":"Support Engineering","job_function_id":null,"job_path":"/en/jobs/3154884/devops-engineer-hosted-execution-hex","job_schedule_type":"full-time","location":"IN, KA, Bengaluru","locations":["{\"normalizedStateName\":\"Karnataka\",\"normalizedCountryCode\":\"IND\",\"city\":\"Bengaluru\",\"countryIso3a\":\"IND\",\"countryIso2a\":\"IN\",\"locationNonStemming\":\"India, KA, Bengaluru\",\"coordinates\":\"12.96617,77.58692\",\"normalizedCountyName\":\"Bengaluru\",\"type\":\"ONSITE\",\"normalizedCountryName\":\"India\",\"normalizedLocation\":\"Bengaluru, Karnataka, IND\",\"location\":\"IN, KA, Bengaluru\",\"region\":\"KA\",\"buildingCodeList\":[\"BLR18\"],\"normalizedCityName\":\"Bengaluru\"}"],"normalized_location":"Bengaluru, Karnataka, IND","optional_search_labels":[],"posted_date":"January  8, 2026","preferred_qualifications":"- Knowledge of web services, distributed systems, and web application development\u003cbr/\u003e- Experience troubleshooting \u0026 maintaining hardware \u0026 software RAID\u003cbr/\u003e- Experience with REST web services, XML, JSON\u003cbr/\u003e\u003cbr/\u003eOur inclusive culture empowers Amazonians to deliver the best results for our customers. If you have a disability and need a workplace accommodation or adjustment during the application and hiring process, including support for the interview or onboarding process, please visit \u003ca href=\"https://amazon.jobs/content/en/how-we-hire/accommodations\"\u003ehttps://amazon.jobs/content/en/how-we-hire/accommodations\u003c/a\u003e for more information. If the country/region you’re applying in isn’t listed, please contact your Recruiting Partner.","primary_search_label":"ecp.builder-works","source_system":"JobCreator","state":"KA","title":"Devops Engineer, Hosted Execution (HEX)","university_job":null,"updated_time":"9 minutes","url_next_step":"https://account.amazon.com/jobs/3154884/apply","team":{"id":null,"business_category_id":null,"identifier":null,"label":"builder-works","created_at":null,"updated_at":null,"image_file_name":null,"image_content_type":null,"image_file_size":null,"image_updated_at":null,"thumbnail_file_name":null,"thumbnail_content_type":null,"thumbnail_file_size":null,"thumbnail_updated_at":null,"hide_jobs":null,"title":null,"headline":null,"description":null}},{"basic_qualifications":"- Diplôme d'ingénieur, d'école de commerce ou d'université\u003cbr/\u003e- Expérience en management d'équipes importantes\u003cbr/\u003e- Expérience en analyse de données\u003cbr/\u003e- Capacité à communiquer en français et en anglais (oral et écrit)","business_category":"fulfillment-ops","city":"Boves","company_name":"Amazon France Logistique SAS","country_code":"FRA","description":"Les opérations représentent la force motrice d’Amazon. Ce service clé de notre activité nous permet d’exécuter et d’expédier les commandes de manière efficace afin que nos clients reçoivent leurs articles en temps et en heure. En tant que responsable de secteur, vous veillerez à ce que votre site fonctionne parfaitement afin de répondre à la demande de nos clients. Vous serez à la tête d’une équipe qui contribue à la sécurité, à l’efficacité et à la qualité de nos opérations et vous prendrez en charge un certain nombre de projets sur l’ensemble de notre réseau afin de stimuler la productivité. \u003cbr/\u003e\u003cbr/\u003eKey job responsibilities\u003cbr/\u003eCréer, superviser et encourager une culture de la sécurité et du bien-être\u003cbr/\u003eAnalyser et mettre en œuvre des changements pour maintenir la qualité et la productivité à un niveau élevé et constant\u003cbr/\u003eSuperviser les projets visant à rationaliser les processus, à optimiser la productivité et à améliorer la qualité du service pour les clients dans votre périmètre de responsabilité\u003cbr/\u003eAnalyser les performances de l’équipe par rapport aux objectifs de l’entreprise et mettre en place des actions pour améliorer notre excellence opérationnelle\u003cbr/\u003eTravailler en collaboration avec des collègues de la direction pour normaliser les pratiques des équipes\u003cbr/\u003e\u003cbr/\u003eA day in the life\u003cbr/\u003eVous travaillerez en équipe sur l’un de nos sites, en veillant à ce qu’il soit aussi productif que possible. Vous aurez pour tâche principale d’instaurer une culture de la sécurité et de faire respecter les normes de qualité et de performance de l’équipe. Vous superviserez également les améliorations apportées aux processus dans votre secteur et en assurerez la mise en œuvre. Vos missions seront variées au cours d’une journée type : gestion de l’équipe, pilotage des opérations quotidiennes, amélioration des processus, missions d’urgence à grande échelle, etc. Vous servirez également d’exemple et de mentor aux nouveaux managers.\u003cbr/\u003e\u003cbr/\u003eAbout the team\u003cbr/\u003eNotre centre de traitement des commandes (Customer Fulfilment, ou CF), est l’endroit où tout a commencé pour Amazon. D’une modeste équipe de libraires, le CF est devenu une équipe mondiale spécialisée qui traite plus de 1,5 million de commandes chaque jour. L’équipe CF est le moteur de notre entreprise et ses efforts nous ont permis de nous tourner vers de nouvelles régions et de proposer de nouveaux services. Avec l’aide des technologies émergentes, nous sommes en permanence à la recherche de solutions nouvelles pour proposer une gamme de produits plus large et de meilleure qualité, livrée rapidement et à un prix abordable.\u003cbr/\u003eL’équipe CF est le premier maillon de la chaîne qui permet aux clients d’obtenir les produits à la vitesse qui fait notre réputation. Nous sommes basés dans les centres de traitement des commandes, qui sont au cœur du réseau des opérations d’Amazon. Nos centres sont parfois appelés le « premier kilomètre », car c’est là que la plupart des colis Amazon commencent leur voyage. Nous aidons à gérer les stocks dynamiques et à faciliter les livraisons rapides, 24 heures sur 24, 7 jours sur 7.\u003cbr/\u003eNos centres de traitement des commandes regroupent des profils variés et les opportunités y sont nombreuses. Certains membres de l’équipe travaillent avec des produits physiques, tandis que d’autres analysent des données. Ensemble, nous travaillons pour que chacun puisse prendre des décisions éclairées dans toute l’entreprise.","department_cost_center":null,"description_short":"Les opérations représentent la force motrice d’Amazon. Ce service clé de notre activité nous permet d’exécuter et d’expédier les commandes de manière efficace afin que nos clients reçoivent leurs articles","display_distance":null,"id":"c354a2ba-4edd-40ec-a347-b381e16657dc","id_icims":"3161144","is_intern":null,"is_manager":null,"job_category":"Fulfillment \u0026 Operations Management","job_family":"Fulfillment Center","job_function_id":null,"job_path":"/en/jobs/3161144/responsable-d-equipe-logistique-h-f-debut-juin","job_schedule_type":"full-time","location":"FR, Boves","locations":["{\"normalizedStateName\":\"Hauts-de-France\",\"normalizedCountryCode\":\"FRA\",\"city\":\"Boves\",\"countryIso3a\":\"FRA\",\"countryIso2a\":\"FR\",\"locationNonStemming\":\"France, Boves\",\"coordinates\":\"49.84859,2.39268\",\"normalizedCountyName\":\"Somme\",\"type\":\"ONSITE\",\"normalizedCountryName\":\"France\",\"normalizedLocation\":\"Boves, Hauts-de-France, FRA\",\"location\":\"FR, Boves\",\"region\":\"\",\"buildingCodeList\":[\"BVA1\"],\"normalizedCityName\":\"Boves\"}"],"normalized_location":"Boves, Hauts-de-France, FRA","optional_search_labels":[],"posted_date":"January 16, 2026","preferred_qualifications":"- Certification Lean ou Six Sigma\u003cbr/\u003e- Expérience dans un environnement industriel, logistique ou de transport\u003cbr/\u003e\u003cbr/\u003eAmazon est un employeur engagé pour l'égalité des chances. Nous sommes convaincus qu'une main d'oeuvre diversifée est essentielle à notre réussite. Nous prenons nos décisions de recrutement en fonction de votre expérience et de vos compétences. Nous apprécions votre envie de découvrir, d'inventer, de simplifier et de construire. La protection de votre vie privée et la sécurité de vos données constituent depuis longtemps une priorité absolue pour Amazon. Veuillez consulter notre Politique de Confidentialité pour en savoir plus sur la façon dont nous collectons, utilisons et traitons les données personnelles de nos candidats.\u003cbr/\u003e\u003cbr/\u003eOur inclusive culture empowers Amazonians to deliver the best results for our customers. If you have a disability and need a workplace accommodation or adjustment during the application and hiring process, including support for the interview or onboarding process, please visit \u003ca href=\"https://amazon.jobs/content/en/how-we-hire/accommodations\"\u003ehttps://amazon.jobs/content/en/how-we-hire/accommodations\u003c/a\u003e for more information. If the country/region you’re applying in isn’t listed, please contact your Recruiting Partner.","primary_search_label":"fulfillment-ops.team-fulfillment-center-management","source_system":"JobCreator","state":null,"title":"Responsable d'équipe logistique (H/F) - début juin","university_job":null,"updated_time":"10 minutes","url_next_step":"https://account.amazon.com/jobs/3161144/apply","team":{"id":null,"business_category_id":null,"identifier":null,"label":"team-fulfillment-center-management","created_at":null,"updated_at":null,"image_file_name":null,"image_content_type":null,"image_file_size":null,"image_updated_at":null,"thumbnail_file_name":null,"thumbnail_content_type":null,"thumbnail_file_size":null,"thumbnail_updated_at":null,"hide_jobs":null,"title":null,"headline":null,"description":null}},{"basic_qualifications":"- 6 months to 3 years' of related experience\u003cbr/\u003e- Fluency in Spanish and English.\u003cbr/\u003e- Bachelor’s Degree in Economics, Management, Engineering or related degree required\u003cbr/\u003e- Excellent written and verbal communication skills; able to explain complex concepts simply\u003cbr/\u003e- Interested in new technologies, capable internet user\u003cbr/\u003e- Computer skills (Excel, Word, Outlook, PowerPoint).\u003cbr/\u003e- Ability to work with wide range of people at all decision-making levels.\u003cbr/\u003e- Experience solving analytical problems, either in professional experience (data analysis) or education.","business_category":"eu3p_marketplace","city":"Madrid","company_name":"Amazon EU SARL (Spain Branch) - C16","country_code":"ESP","description":"  Are you looking to join a community of business development professionals that support the growth of small and medium sized businesses?  Does helping others meet their full potential excite you? Amazon, one of the world's leaders in e-commerce is looking for New Account Managers (business-development professionals) to join its Third-Party Marketplace support team based in Madrid, Spain.\u003cbr/\u003e \u003cbr/\u003eYour role will be focused on contributing to new business acquisition through lead generation, phone/email-based business evaluation and supporting the business launch of new sellers – as they make their wide range of products available to millions of Amazon customers. You will also build seller relationships as an account manager  – supporting a seller in their business launch and helping them grow their business on Amazon. In addition to account management, you will be responsible for incorporating feedback from the sellers into new opportunities to improve Amazon’s products, services, processes, systems and tools for all 3rd party sellers.\u003cbr/\u003e \u003cbr/\u003e YOUR RESPONSIBILITIES:\u003cbr/\u003e 1. Identify, prospect and recruit high-potential sellers to Amazon.es website, via phone or email\u003cbr/\u003e 2. Effectively prioritize and lead a pipeline of sellers to consistently meet/exceed quarterly targets\u003cbr/\u003e 3. Be a business partner for new sellers providing them with data-driven insights and advice to optimize their success on the Amazon Platform\u003cbr/\u003e 4. Work closely with new sellers, educating them about Amazon’s high standards of Delivery and Customer Experience\u003cbr/\u003e 5. Enable sellers to learn and master Amazon's tools and systems so they may become self-sufficient in handling their catalog, inventory and performance efficiently and to the required standards\u003cbr/\u003e 6. Learn and understand the specificities of your categories to spot popular brands, trends, seasonal items and pricing to best tailor your pitch and advice to sellers\u003cbr/\u003e 7. Track and report business development results, analyze data, interpret reports and information for your portfolio of sellers\u003cbr/\u003e 8. Prioritize your time optimally to achieve your targets a results oriented environment\u003cbr/\u003e  ","department_cost_center":null,"description_short":"  Are you looking to join a community of business development professionals that support the growth of small and medium sized businesses?  Does helping others meet their full potential excite you? Amazon,","display_distance":null,"id":"1a9ba736-fa07-4757-a1b6-869ca9f982b0","id_icims":"3199160","is_intern":null,"is_manager":null,"job_category":"Sales, Advertising, \u0026 Account Management","job_family":"Sales/Account Management","job_function_id":null,"job_path":"/en/jobs/3199160/new-account-manager-marketplace-spain-amazon-business","job_schedule_type":"full-time","location":"ES, M, Madrid","locations":["{\"normalizedStateName\":\"Community of Madrid\",\"normalizedCountryCode\":\"ESP\",\"city\":\"Madrid\",\"countryIso3a\":\"ESP\",\"countryIso2a\":\"ES\",\"locationNonStemming\":\"Spain, M, Madrid\",\"coordinates\":\"40.42024,-3.68755\",\"normalizedCountyName\":\"Madrid\",\"type\":\"ONSITE\",\"normalizedCountryName\":\"Spain\",\"normalizedLocation\":\"Madrid, Community of Madrid, ESP\",\"location\":\"ES, M, Madrid\",\"region\":\"M\",\"buildingCodeList\":[\"MAD15\"],\"normalizedCityName\":\"Madrid\"}"],"normalized_location":"Madrid, Community of Madrid, ESP","optional_search_labels":[],"posted_date":"March  9, 2026","preferred_qualifications":"- Experience in outbound sales.\u003cbr/\u003e- Experience in e-commerce or retail.\u003cbr/\u003e- Demonstrated track record of success in account management, product marketing or management consulting roles.\u003cbr/\u003e\u003cbr/\u003eAmazon is an equal opportunities employer. We believe passionately that employing a diverse workforce is central to our success. We make recruiting decisions based on your experience and skills. We value your passion to discover, invent, simplify and build. Protecting your privacy and the security of your data is a longstanding top priority for Amazon. Please consult our Privacy Notice (\u003ca href=\"https://www.amazon.jobs/en/privacy_page\"\u003ehttps://www.amazon.jobs/en/privacy_page\u003c/a\u003e) to know more about how we collect, use and transfer the personal data of our candidates.\u003cbr/\u003e\u003cbr/\u003eOur inclusive culture empowers Amazonians to deliver the best results for our customers. If you have a disability and need a workplace accommodation or adjustment during the application and hiring process, including support for the interview or onboarding process, please visit \u003ca href=\"https://amazon.jobs/content/en/how-we-hire/accommodations\"\u003ehttps://amazon.jobs/content/en/how-we-hire/accommodations\u003c/a\u003e for more information. If the country/region you’re applying in isn’t listed, please contact your Recruiting Partner.","primary_search_label":"eu3p_marketplace.team-consumer-3p-job-posting","source_system":"JobCreator","state":"M","title":"New Account Manager - Marketplace, Spain, Amazon Business","university_job":null,"updated_time":"12 minutes","url_next_step":"https://account.amazon.com/jobs/3199160/apply","team":{"id":null,"business_category_id":null,"identifier":null,"label":"team-consumer-3p-job-posting","created_at":null,"updated_at":null,"image_file_name":null,"image_content_type":null,"image_file_size":null,"image_updated_at":null,"thumbnail_file_name":null,"thumbnail_content_type":null,"thumbnail_file_size":null,"thumbnail_updated_at":null,"hide_jobs":null,"title":null,"headline":null,"description":null}},{"basic_qualifications":"- Diplôme d'ingénieur, d'école de commerce ou d'université\u003cbr/\u003e- Expérience en management d'équipes importantes\u003cbr/\u003e- Expérience en analyse de données\u003cbr/\u003e- Capacité à communiquer en français et en anglais (oral et écrit)","business_category":"fulfillment-ops","city":"Augny","company_name":"Amazon France Logistique SAS","country_code":"FRA","description":"Les opérations représentent la force motrice d’Amazon. Ce service clé de notre activité nous permet d’exécuter et d’expédier les commandes de manière efficace afin que nos clients reçoivent leurs articles en temps et en heure. En tant que responsable de secteur, vous veillerez à ce que votre site fonctionne parfaitement afin de répondre à la demande de nos clients. Vous serez à la tête d’une équipe qui contribue à la sécurité, à l’efficacité et à la qualité de nos opérations et vous prendrez en charge un certain nombre de projets sur l’ensemble de notre réseau afin de stimuler la productivité. \u003cbr/\u003e\u003cbr/\u003eKey job responsibilities\u003cbr/\u003eCréer, superviser et encourager une culture de la sécurité et du bien-être\u003cbr/\u003eAnalyser et mettre en œuvre des changements pour maintenir la qualité et la productivité à un niveau élevé et constant\u003cbr/\u003eSuperviser les projets visant à rationaliser les processus, à optimiser la productivité et à améliorer la qualité du service pour les clients dans votre périmètre de responsabilité\u003cbr/\u003eAnalyser les performances de l’équipe par rapport aux objectifs de l’entreprise et mettre en place des actions pour améliorer notre excellence opérationnelle\u003cbr/\u003eTravailler en collaboration avec des collègues de la direction pour normaliser les pratiques des équipes\u003cbr/\u003e\u003cbr/\u003eA day in the life\u003cbr/\u003eVous travaillerez en équipe sur l’un de nos sites, en veillant à ce qu’il soit aussi productif que possible. Vous aurez pour tâche principale d’instaurer une culture de la sécurité et de faire respecter les normes de qualité et de performance de l’équipe. Vous superviserez également les améliorations apportées aux processus dans votre secteur et en assurerez la mise en œuvre. Vos missions seront variées au cours d’une journée type : gestion de l’équipe, pilotage des opérations quotidiennes, amélioration des processus, missions d’urgence à grande échelle, etc. Vous servirez également d’exemple et de mentor aux nouveaux managers.\u003cbr/\u003e\u003cbr/\u003eAbout the team\u003cbr/\u003eNotre centre de traitement des commandes (Customer Fulfilment, ou CF), est l’endroit où tout a commencé pour Amazon. D’une modeste équipe de libraires, le CF est devenu une équipe mondiale spécialisée qui traite plus de 1,5 million de commandes chaque jour. L’équipe CF est le moteur de notre entreprise et ses efforts nous ont permis de nous tourner vers de nouvelles régions et de proposer de nouveaux services. Avec l’aide des technologies émergentes, nous sommes en permanence à la recherche de solutions nouvelles pour proposer une gamme de produits plus large et de meilleure qualité, livrée rapidement et à un prix abordable.\u003cbr/\u003eL’équipe CF est le premier maillon de la chaîne qui permet aux clients d’obtenir les produits à la vitesse qui fait notre réputation. Nous sommes basés dans les centres de traitement des commandes, qui sont au cœur du réseau des opérations d’Amazon. Nos centres sont parfois appelés le « premier kilomètre », car c’est là que la plupart des colis Amazon commencent leur voyage. Nous aidons à gérer les stocks dynamiques et à faciliter les livraisons rapides, 24 heures sur 24, 7 jours sur 7.\u003cbr/\u003eNos centres de traitement des commandes regroupent des profils variés et les opportunités y sont nombreuses. Certains membres de l’équipe travaillent avec des produits physiques, tandis que d’autres analysent des données. Ensemble, nous travaillons pour que chacun puisse prendre des décisions éclairées dans toute l’entreprise.","department_cost_center":null,"description_short":"Les opérations représentent la force motrice d’Amazon. Ce service clé de notre activité nous permet d’exécuter et d’expédier les commandes de manière efficace afin que nos clients reçoivent leurs articles","display_distance":null,"id":"85dff114-6362-4f0a-9dd4-4de0b34b08c1","id_icims":"3161123","is_intern":null,"is_manager":null,"job_category":"Fulfillment \u0026 Operations Management","job_family":"Fulfillment Center","job_function_id":null,"job_path":"/en/jobs/3161123/responsable-d-equipe-logistique-h-f-debut-juin","job_schedule_type":"full-time","location":"FR, Augny","locations":["{\"normalizedStateName\":\"Grand Est\",\"normalizedCountryCode\":\"FRA\",\"city\":\"Augny\",\"countryIso3a\":\"FRA\",\"countryIso2a\":\"FR\",\"locationNonStemming\":\"France, Augny\",\"coordinates\":\"49.05906,6.12152\",\"normalizedCountyName\":\"Moselle\",\"type\":\"ONSITE\",\"normalizedCountryName\":\"France\",\"normalizedLocation\":\"Augny, Grand Est, FRA\",\"location\":\"FR, Augny\",\"region\":\"\",\"buildingCodeList\":[\"ETZ2\"],\"normalizedCityName\":\"Augny\"}"],"normalized_location":"Augny, Grand Est, FRA","optional_search_labels":[],"posted_date":"January 16, 2026","preferred_qualifications":"- Certification Lean ou Six Sigma\u003cbr/\u003e- Expérience dans un environnement industriel, logistique ou de transport\u003cbr/\u003e\u003cbr/\u003eAmazon est un employeur engagé pour l'égalité des chances. Nous sommes convaincus qu'une main d'oeuvre diversifée est essentielle à notre réussite. Nous prenons nos décisions de recrutement en fonction de votre expérience et de vos compétences. Nous apprécions votre envie de découvrir, d'inventer, de simplifier et de construire. La protection de votre vie privée et la sécurité de vos données constituent depuis longtemps une priorité absolue pour Amazon. Veuillez consulter notre Politique de Confidentialité pour en savoir plus sur la façon dont nous collectons, utilisons et traitons les données personnelles de nos candidats.\u003cbr/\u003e\u003cbr/\u003eOur inclusive culture empowers Amazonians to deliver the best results for our customers. If you have a disability and need a workplace accommodation or adjustment during the application and hiring process, including support for the interview or onboarding process, please visit \u003ca href=\"https://amazon.jobs/content/en/how-we-hire/accommodations\"\u003ehttps://amazon.jobs/content/en/how-we-hire/accommodations\u003c/a\u003e for more information. If the country/region you’re applying in isn’t listed, please contact your Recruiting Partner.","primary_search_label":"fulfillment-ops.team-fulfillment-center-management","source_system":"JobCreator","state":null,"title":"Responsable d'équipe logistique (H/F) -  début juin","university_job":null,"updated_time":"13 minutes","url_next_step":"https://account.amazon.com/jobs/3161123/apply","team":{"id":null,"business_category_id":null,"identifier":null,"label":"team-fulfillment-center-management","created_at":null,"updated_at":null,"image_file_name":null,"image_content_type":null,"image_file_size":null,"image_updated_at":null,"thumbnail_file_name":null,"thumbnail_content_type":null,"thumbnail_file_size":null,"thumbnail_updated_at":null,"hide_jobs":null,"title":null,"headline":null,"description":null}},{"basic_qualifications":"- Experience in MS Excel, Word, and Windows Operating Systems\u003cbr/\u003e- Knowledge of critical data center equipment\u003cbr/\u003e- Experience working in a data center or mission critical facility (example: hospital, military facility, public safety facility, etc.)\u003cbr/\u003e- Experience managing technical programs across cross-functional teams, building processes and coordinating release schedules","business_category":"aws","city":"Dublin","company_name":"Amazon Data Services Ireland Limited","country_code":"IRL","description":"At Amazon, we're working to be the most customer-centric company on earth! Amazon is a place where builders can build. We hire the world's brightest minds and offer them an environment in which they can invent and innovate to improve the experience for our customers. If you'd like to help us build a place where you can find and buy anything online, this is the job for you. \u003cbr/\u003e\u003cbr/\u003eThe AWS Data Center Community (DCC) organization is looking for an individual with proven and tested leadership skills to join the Facility Operation Center (FOC) team. The FOC launched as a singular support team to proactively monitor the life-safety systems and the infrastructure equipment alarms that provides power and cooling to the platform on a global 24x7x365 basis. We support Data Center Engineer Operations teams who are responsible for the operation of infrastructure equipment.  \u003cbr/\u003e\u003cbr/\u003eThe FOC Technical Specialist facilitates and deep dives customer impacting events, locates systemic infrastructure issues using data driven analysis to drive solutions and serves as a subject matter expert on department processes. The FOC Technical Specialist is responsible for the design, creation, and launch of new learning content, creating and maintaining all FOC documentation globally, and managing the technical training of the team across the regions. You will play a significant role in the career development of the global FOC team by mentoring and helping managers guide the career growth of their team members. You are responsible for leading team members across regions and functional areas to accomplish organizational goals. You will guide the team on improving operational efficiency for all services through the identification and development of SLAs, metrics, workflows, procedures, tools, and documentation. You will lead data analysis and engagement of stakeholder teams to drive corrective actions by utilizing processes, such as After-Action Reports (AAR), Correction of Errors (COE), AWS Emergency Response protocols, Lessons Learned, and Global Action Items. You will be responsible for delivering global projects while influencing stakeholders by creating reports, improving processes, and presenting narratives. You will be expected to run effective projects and programs independently. You will support team goals and projects by providing feedback and technical support as required.  \u003cbr/\u003e\u003cbr/\u003eKey job responsibilities\u003cbr/\u003e- Provides support to the team during Critical Site (CSE) and Large Scale (LSE) events. Acts as FOC POC in the COE process. \u003cbr/\u003e- Deep dives post event data and reviews all After Action Reports (AAR) to ensure standards are met. \u003cbr/\u003e- Meet or exceed FOC KPI’s in project delivery to develop and drive FOC Engineer. efficiency projects which reduce manual tasks. \u003cbr/\u003e- Meet or exceed FOC KPI’s in tracking project/program quality of 85%. \u003cbr/\u003e- Author and present AWS business continuity and emergency response program documents. \u003cbr/\u003e- Ability to lead DC availability meetings and post event analysis to senior leadership. \u003cbr/\u003e- Ownership and driving organizational and team level goals \u003cbr/\u003e- Continuous integration with stakeholder teams on program improvements. \u003cbr/\u003e- Locates systemic infrastructure issues using data driven analysis to drive solutions. \u003cbr/\u003e- Collaborates with external teams to implement new processes to reduce waste. \u003cbr/\u003e- Creates and maintains FOC technical documentation driving process improvements. \u003cbr/\u003e- Manages technical training to ensure engineers meet the bar for engineering knowledge. \u003cbr/\u003e- Designs, creates and implements learning content, practical assessments, and facilitates workshops and instructor led training programs. \u003cbr/\u003e- Develops certification mechanisms to further enhance operational excellence, professional and career development. \u003cbr/\u003e\u003cbr/\u003eAbout the team\u003cbr/\u003eDiverse Experiences\u003cbr/\u003eAWS values diverse experiences. Even if you do not meet all of the qualifications and skills listed in the job description, we encourage candidates to apply. If your career is just starting, hasn’t followed a traditional path, or includes alternative experiences, don’t let it stop you from applying.\u003cbr/\u003e\u003cbr/\u003eWhy AWS?\u003cbr/\u003eAmazon Web Services (AWS) is the world’s most comprehensive and broadly adopted cloud platform. We pioneered cloud computing and never stopped innovating — that’s why customers from the most successful startups to Global 500 companies trust our robust suite of products and services to power their businesses.\u003cbr/\u003e\u003cbr/\u003eInclusive Team Culture\u003cbr/\u003eHere at AWS, it’s in our nature to learn and be curious. Our employee-led affinity groups foster a culture of inclusion that empower us to be proud of our differences. Ongoing events and learning experiences, including our Conversations on Race and Ethnicity (CORE) and AmazeCon (diversity) conferences, inspire us to never stop embracing our uniqueness.\u003cbr/\u003e\u003cbr/\u003eMentorship \u0026 Career Growth\u003cbr/\u003eWe’re continuously raising our performance bar as we strive to become Earth’s Best Employer. That’s why you’ll find endless knowledge-sharing, mentorship and other career-advancing resources here to help you develop into a better-rounded professional.\u003cbr/\u003e\u003cbr/\u003eWork/Life Balance\u003cbr/\u003eWe value work-life harmony. Achieving success at work should never come at the expense of sacrifices at home, which is why flexible work hours and arrangements are part of our culture. When we feel supported in the workplace and at home, there’s nothing we can’t achieve in the cloud.","department_cost_center":null,"description_short":"At Amazon, we're working to be the most customer-centric company on earth! Amazon is a place where builders can build. We hire the world's brightest minds and offer them an environment in which they can","display_distance":null,"id":"d1be88ba-8d93-4eb3-af9e-4d0f6c393f05","id_icims":"10376780","is_intern":null,"is_manager":null,"job_category":"Operations, IT, \u0026 Support Engineering","job_family":"Tech Ops Engineering","job_function_id":null,"job_path":"/en/jobs/10376780/facility-operations-technical-specialist-facility-operations-center","job_schedule_type":"full-time","location":"IE, D, Dublin","locations":["{\"normalizedCountryCode\":\"IRL\",\"city\":\"Dublin\",\"countryIso3a\":\"IRL\",\"countryIso2a\":\"IE\",\"locationNonStemming\":\"Ireland, D, Dublin\",\"coordinates\":\"53.34807,-6.24827\",\"normalizedCountyName\":\"County Dublin\",\"type\":\"ONSITE\",\"normalizedCountryName\":\"Ireland\",\"normalizedLocation\":\"Dublin, IRL\",\"location\":\"IE, D, Dublin\",\"region\":\"D\",\"buildingCodeList\":[\"DUB50\"],\"normalizedCityName\":\"Dublin\"}"],"normalized_location":"Dublin, IRL","optional_search_labels":[],"posted_date":"March 26, 2026","preferred_qualifications":"- Bachelor's degree in Electrical Engineering, Mechanical Engineering, or a related field\u003cbr/\u003e- Knowledge of engineering documentation, electrical diagrams and standard operating procedures\u003cbr/\u003e- Experience in project management in data centers or comparable critical infrastructure\u003cbr/\u003e- Experience in Data Center Engineering Operations, with a deep understanding of electrical and mechanical data center infrastructure\u003cbr/\u003e\u003cbr/\u003eAmazon is an equal opportunities employer. We believe passionately that employing a diverse workforce is central to our success. We make recruiting decisions based on your experience and skills. We value your passion to discover, invent, simplify and build. Protecting your privacy and the security of your data is a longstanding top priority for Amazon. Please consult our Privacy Notice (\u003ca href=\"https://www.amazon.jobs/en/privacy_page\"\u003ehttps://www.amazon.jobs/en/privacy_page\u003c/a\u003e) to know more about how we collect, use and transfer the personal data of our candidates.\u003cbr/\u003e\u003cbr/\u003eAmazon is an equal opportunity employer and does not discriminate on the basis of protected veteran status, disability, or other legally protected status.\u003cbr/\u003e\u003cbr/\u003eOur inclusive culture empowers Amazonians to deliver the best results for our customers. If you have a disability and need a workplace accommodation or adjustment during the application and hiring process, including support for the interview or onboarding process, please visit \u003ca href=\"https://amazon.jobs/content/en/how-we-hire/accommodations\"\u003ehttps://amazon.jobs/content/en/how-we-hire/accommodations\u003c/a\u003e for more information. If the country/region you’re applying in isn’t listed, please contact your Recruiting Partner.","primary_search_label":"aws.team-support-engineer-primary","source_system":"JobCreator","state":"D","title":"Facility Operations Technical Specialist, Facility Operations Center","university_job":null,"updated_time":"17 minutes","url_next_step":"https://account.amazon.com/jobs/10376780/apply","team":{"id":null,"business_category_id":null,"identifier":null,"label":"team-support-engineer-primary","created_at":null,"updated_at":null,"image_file_name":null,"image_content_type":null,"image_file_size":null,"image_updated_at":null,"thumbnail_file_name":null,"thumbnail_content_type":null,"thumbnail_file_size":null,"thumbnail_updated_at":null,"hide_jobs":null,"title":null,"headline":null,"description":null}},{"basic_qualifications":"- Bachelor's degree or equivalent\u003cbr/\u003e- Experience in compliance program management, legal, governance, audit, risk/loss prevention, or equivalent\u003cbr/\u003e- Experience handling confidential information\u003cbr/\u003e- Experience in compliance, audit or risk management\u003cbr/\u003e- Experience handling confidential information","business_category":"selling-partner-services","city":"Virtual","company_name":"ADCI - BLR 14 SEZ - F07","country_code":"IND","description":"Amazon Payments entities operate as regulated financial services providers across multiple jurisdictions, subject to stringent third-party risk management requirements. Some examples include CSSF Circular 22/806 (Luxembourg), EBA Guidelines on Outsourcing and FCA SYSC 8 (UK), and MAS Guidelines on Outsourcing (Singapore).\u003cbr/\u003e\u003cbr/\u003eWe are seeking an experienced Third-Party Risk Management (TPRM) professional to join our Account Compliance team as an Outsourcing Risk Manager. This role requires demonstrated expertise in conducting outsourcing risk assessments for regulated financial institutions, with specific knowledge of regulatory frameworks governing critical and important outsourcing arrangements.\u003cbr/\u003e\u003cbr/\u003eYou will be responsible for executing the First Line outsourcing risk management program for Amazon Payments' regulated entities (APE, APUK, API, APS SG, and others). This includes conducting annual risk assessments of intragroup and external vendor arrangements, partnering with Legal and Transfer Pricing teams to manage intercompany contracts, establishing KPIs and governance mechanisms to monitor service delivery, partnering with business teams to implement risk-mitigation controls, and ensuring compliance with entity-specific regulatory requirements.\u003cbr/\u003e\u003cbr/\u003eThis is a critical role enabling Amazon Payments to scale globally while maintaining robust regulatory compliance. The ideal candidate will have hands-on experience performing risk assessments under frameworks such as CSSF 22/806, EBA Guidelines on Outsourcing, FCA SYSC 8, or equivalent regulatory regimes, and can demonstrate practical application of outsourcing risk management principles in a regulated financial services environment.\u003cbr/\u003e\u003cbr/\u003eKey job responsibilities\u003cbr/\u003e• Lead First Line Risk Management for Amazon's outsourcing arrangements between internal Amazon entities and external vendors, establishing strategic partnerships with Second Line departments to ensure robust risk governance and regulatory compliance.\u003cbr/\u003e\u003cbr/\u003e• Own and execute annual risk assessments for services between Amazon entities and external vendors, including comprehensive information gathering with partner teams, developing detailed risk assessments, and securing final approvals from Risk, Compliance, Legal, and Information Security stakeholders within established timelines.\u003cbr/\u003e\u003cbr/\u003e• Partner strategically with Legal and Transfer Pricing, to maintain existing intragroup contracts to ensure service scope, KPIs, and terms remain aligned with evolving business requirements and regulatory obligations.\u003cbr/\u003e\u003cbr/\u003e• Collaborate with partner teams to proactively identify risks, establish effective mitigation controls with clear delivery timelines, and define KPIs to track and measure performance against contractual obligations.\u003cbr/\u003e\u003cbr/\u003e• Create and maintain robust documentation serving as an audit trail for Amazon Payments Compliance functions, insisting on the highest standards and embedding an 'audit-ready' mentaility.\u003cbr/\u003e\u003cbr/\u003e• Collaborate with Business Intelligence Engineers and Analysts to design, build, and automate reporting mechanisms, while establishing escalation protocols for KPIs that breach contractual obligations, ensuring timely remediation and stakeholder visibility.\u003cbr/\u003e\u003cbr/\u003e• Enable business expansion by partnering with Business Expansion, Risk, and Compliance teams to establish compliant intragroup outsourcing structures for new legal entity launches and manage vendor onboarding processes in accordance with regulatory requirements, including preparation of regulatory notifications and submissions where required.\u003cbr/\u003e\u003cbr/\u003e• Drive continuous improvement by identifying and executing opportunities to enhance operational efficiency through standardization and automation, working cross-functionally across Compliance, Operations, Risk, and Analytics teams to prioritize and deliver measurable improvements.\u003cbr/\u003e\u003cbr/\u003e• Champion a culture of compliance by proactively engaging with on-site partner teams, driving higher quality inputs, reinforcing compliance concepts, and fostering a risk-aware environment across all outsourcing activities.\u003cbr/\u003e\u003cbr/\u003eA day in the life\u003cbr/\u003eYou'll conduct risk assessments for critical vendors, analyzing due diligence questionnaires to identify control gaps. You'll partner with Legal and Transfer Pricing on intragroup contract amendments, ensuring regulatory compliant clauses. You'll conduct outsourcing categorization assessments for new jurisdictions, guiding business teams through regulatory due diligence requirements. You'll monitor service providers KPIs, identifying SLA breaches requiring investigation, and prepare quarterly Board(s) reporting on outsourcing arrangements. Throughout the day, you'll collaborate with a range of stakeholders (Second Line Risk and Compliance Officers, Information Security, Legal teams, business stakeholders, providing guidance on policy interpretation and regulatory obligations while balancing compliance precision with business pragmatism. You will be driving risk mitigation actions.\u003cbr/\u003e\u003cbr/\u003eAbout the team\u003cbr/\u003eYou'll join the Account Compliance Risk \u0026 Quality team in TSI, serving as First Line of Defense for outsourcing risk management across Amazon Payments' regulated entities. We operate at the intersection of regulatory compliance, risk management, and business enablement—ensuring Amazon Payments meets regulatory obligations while supporting global scaling. We partner closely with Second Line Risk \u0026 Compliance, Legal, Information Security, Finance, Tax, Transfer Pricing, and business stakeholders across multiple jurisdictions. We value regulatory expertise, practical problem-solving, working through ambiguity, and translating complex compliance requirements into actionable guidance. Our culture emphasizes collaboration, continuous learning, and maintaining highest regulatory standards while enabling business innovation.","department_cost_center":null,"description_short":"Amazon Payments entities operate as regulated financial services providers across multiple jurisdictions, subject to stringent third-party risk management requirements. Some examples include CSSF Circular","display_distance":null,"id":"3bf434cc-72c1-48a9-a88a-5de0f63e6b00","id_icims":"10384850","is_intern":null,"is_manager":null,"job_category":"Project/Program/Product Management--Non-Tech","job_family":"Risk Family","job_function_id":null,"job_path":"/en/jobs/10384850/outsourcing-risk-manager-account-compliance","job_schedule_type":"full-time","location":"IN, BR, Virtual","locations":["{\"normalizedStateName\":\"Bihar\",\"normalizedCountryCode\":\"IND\",\"city\":\"Virtual\",\"countryIso3a\":\"IND\",\"countryIso2a\":\"IN\",\"locationNonStemming\":\"India, BR, Virtual\",\"coordinates\":\"25.60134,85.13752\",\"type\":\"VIRTUAL\",\"normalizedCountryName\":\"India\",\"normalizedLocation\":\"Bihar, IND\",\"location\":\"IN, BR, Virtual\",\"region\":\"BR\",\"buildingCodeList\":[\"VIR\"]}"],"normalized_location":"Bihar, IND","optional_search_labels":[],"posted_date":"April  7, 2026","preferred_qualifications":"- Professional auditing qualification, or similar risk or compliance credentials\u003cbr/\u003e- Experience in program requirements definition, together with data and metrics leveraging to drive improvements\u003cbr/\u003e- Experience in Excel or SQL\u003cbr/\u003e- Experience defining program requirements and using data and metrics to drive improvements\u003cbr/\u003e\u003cbr/\u003eOur inclusive culture empowers Amazonians to deliver the best results for our customers. If you have a disability and need a workplace accommodation or adjustment during the application and hiring process, including support for the interview or onboarding process, please visit \u003ca href=\"https://amazon.jobs/content/en/how-we-hire/accommodations\"\u003ehttps://amazon.jobs/content/en/how-we-hire/accommodations\u003c/a\u003e for more information. If the country/region you’re applying in isn’t listed, please contact your Recruiting Partner.","primary_search_label":"selling-partner-services.team-selling-partner-risk","source_system":"JobCreator","state":"BR","title":"Outsourcing Risk Manager, Account Compliance ","university_job":null,"updated_time":"18 minutes","url_next_step":"https://account.amazon.com/jobs/10384850/apply","team":{"id":null,"business_category_id":null,"identifier":null,"label":"team-selling-partner-risk","created_at":null,"updated_at":null,"image_file_name":null,"image_content_type":null,"image_file_size":null,"image_updated_at":null,"thumbnail_file_name":null,"thumbnail_content_type":null,"thumbnail_file_size":null,"thumbnail_updated_at":null,"hide_jobs":null,"title":null,"headline":null,"description":null}},{"basic_qualifications":"- Abgeschlossenes Hochschulstudium vor dem Starttermin oder Abschluss innerhalb der letzten 24 Monate\u003cbr/\u003e- Fortgeschrittene Englisch- und Deutschkenntnisse in Wort und Schrift\u003cbr/\u003e- Relevante Erfahrung in der Durchführung von Datenanalysen","business_category":"fulfillment-and-operations","city":"Straubing","company_name":"Amazon Deutschland S3 Transport GmbH","country_code":"DEU","description":"Als Nachwuchsführungskraft wirst du in unserem 11-wöchigen internen Onboarding Programm auf deine neue Aufgabe als Führungskraft vorbereitet.\u003cbr/\u003eNach dieser umfangreichen Einarbeitung übernimmst du Führungsverantwortung für dein eigenes Team und sorgst dafür, dass unsere Kunden Ihre Waren pünktlich und in guter Qualität erhalten. In dieser Position bist du wichtiger Teil unseres globalen Unternehmens und arbeitest Hand in Hand mit deinen Mitarbeitenden vor Ort. Zudem arbeitest du standortübergreifend an Themen wie Arbeitssicherheit, Prozessoptimierung, Nachhaltigkeit und technischem Fortschritt.\u003cbr/\u003e\u003cbr/\u003e\u003cbr/\u003eKey job responsibilities\u003cbr/\u003e•\tSicherstellung der Einhaltung der Arbeitssicherheitsvorschriften und des Umweltschutzes\u003cbr/\u003e•\tAbleitung von Handlungsempfehlungen und konkreten Maßnahmen zur Prozessverbesserung auf Basis von Kennzahlen wie Arbeitssicherheit, Produktivität und Qualität\u003cbr/\u003e•\tLeitung und Weiterbildung eines Teams (bis zu 100 Mitarbeitende)\u003cbr/\u003e•\tPlanung und Steuerung der innerbetrieblichen Prozesse\u003cbr/\u003e•\tTeilnahme in übergeordneten Projekten zur Optimierung der Kundenzufriedenheit\u003cbr/\u003e•\tEffektives Ressourcen- und Workflowmanagement\u003cbr/\u003e•\tZusammenarbeit mit den vor- und nachgelagerten Abteilungen vor Ort\u003cbr/\u003e\u003cbr/\u003e\u003cbr/\u003eA day in the life\u003cbr/\u003eDu arbeitest in einer unserer Schichten (Früh-, Spät- oder Nachtschicht). Dabei ist das Einhalten der Sicherheitsstandards an deinem gesamten Standort für dich höchste Priorität. Als Schichtleitung führst du routinemäßig Teammeetings durch und führst Feedbackgespräche mit deinen Mitarbeitenden und deinen Stakeholdern. Mit Hilfe von Datenauswertungen nimmst Du Einfluss auf die Produktivität und die Qualität deines Standortes. Als wichtiges Mitglied des Teams vor Ort arbeitest Du mit anderen Abteilungen, sowie externen Stakeholdern zusammen und sorgst dafür, dass wir die Anforderungen unserer Kundschaft, ebenso wie unsere eigenen Vorgaben jederzeit erfüllen. Durch die Analyse von Daten mit Führungskräften und die Besprechung der betrieblichen Vor- und Nachteile von technischen Verbesserungen mit den Fachabteilungen trägst du zu „best in class“ Lösungen bei.\u003cbr/\u003e\u003cbr/\u003eAbout the team\u003cbr/\u003eAmazon Logistik (AMZL) ist für die Auslieferung von Millionen von Produkten unserer Kunden und Kundinnen direkt an die Haustür verantwortlich. Die „Last-Mile-Logistik“ liefert unsere Pakete in Partnerschaft mit Drittanbietern und realisiert zahlreiche Initiativen zur kontinuierlichen Verbesserung, um Millionen von Kunden zufrieden zu stellen.\u003cbr/\u003eUnser Ziel ist es, das Liefererlebnis für unsere Kund:innen so reibungslos wie möglich zu machen und globale Lieferlösungen für unsere neuesten Angebote einzuführen, darunter Amazon Fresh, Prime Now und Amazon Restaurants.\u003cbr/\u003eUnsere Arbeit lässt sich in zwei Sparten unterteilen. „Under the Roof“ betrifft alles was innerhalb unserer Logistikstandorte passiert und „On the Road“ alles was in den Liefergebieten auf der Straße stattfindet. Unsere Mitarbeitenden bereiten die Pakete in entsprechenden Schichten (Nacht, Früh, Spät) auf den täglichen Versand an unsere Lieferteams vor und kümmern sich um Retouren, die nicht ausgeliefert werden konnten.\u003cbr/\u003eJedes Jahr setzen wir neue Maßstäbe in puncto Kundenerlebnis und bieten neue, innovative Lieferdienste an. Wir suchen nach neuen Möglichkeiten, um branchenweite Logistikherausforderungen zu überwinden, sowie nach neuen Ideen, um unseren CO2-Fußabdruck zu reduzieren. Ein Fuhrpark innovativer Fahrzeuge (einschließlich E-Fahrzeugen) und modernste Technologie unterstützen uns dabei.","department_cost_center":null,"description_short":"Als Nachwuchsführungskraft wirst du in unserem 11-wöchigen internen Onboarding Programm auf deine neue Aufgabe als Führungskraft vorbereitet.Nach dieser umfangreichen Einarbeitung übernimmst du Führungsverantwortung","display_distance":null,"id":"c29a7152-deb5-48b8-856e-dbb1eefb3949","id_icims":"10394540","is_intern":null,"is_manager":null,"job_category":"Fulfillment \u0026 Operations Management","job_family":"Fulfillment Center","job_function_id":null,"job_path":"/en/jobs/10394540/graduate-logistik-manager-straubing-bayern","job_schedule_type":"full-time","location":"DE, ST, Straubing","locations":["{\"normalizedStateName\":\"Bavaria\",\"normalizedCountryCode\":\"DEU\",\"city\":\"Straubing\",\"countryIso3a\":\"DEU\",\"countryIso2a\":\"DE\",\"locationNonStemming\":\"Germany, ST, Straubing\",\"coordinates\":\"48.88197,12.57384\",\"normalizedCountyName\":\"Straubing\",\"type\":\"ONSITE\",\"normalizedCountryName\":\"Germany\",\"normalizedLocation\":\"Straubing, Bavaria, DEU\",\"location\":\"DE, ST, Straubing\",\"region\":\"ST\",\"buildingCodeList\":[\"DBX9\"],\"normalizedCityName\":\"Straubing\"}"],"normalized_location":"Straubing, Bavaria, DEU","optional_search_labels":["university-ops-europe-full-time"],"posted_date":"April 17, 2026","preferred_qualifications":"- Aktuelles Studium oder kürzlich erworbener Bachelor- oder Masterabschluss im Bereich Logistik, Wirtschaftswissenschaften, Ingenieurwesen oder in einem vergleichbaren Studiengang\u003cbr/\u003e- Interesse eine Führungsaufgabe und ein eigenes Team mit Mitarbeitenden aus der ganzen Welt zu übernehmen\u003cbr/\u003e- Erfahrung in der Kommunikation mit verschiedenen Stakeholdern, einschließlich Kolleg:innen und Führungskräften\u003cbr/\u003e- Erfahrung in einer Logistikumgebung\u003cbr/\u003e- Erfahrung in der Arbeit mit MS Office (Word, Excel, Outlook) im beruflichen Umfeld\u003cbr/\u003e\u003cbr/\u003eAmazon is an equal opportunities employer. We believe passionately that employing a diverse workforce is central to our success. We make recruiting decisions based on your experience and skills. We value your passion to discover, invent, simplify and build. Protecting your privacy and the security of your data is a longstanding top priority for Amazon. Please consult our Privacy Notice (\u003ca href=\"https://www.amazon.jobs/en/privacy_page\"\u003ehttps://www.amazon.jobs/en/privacy_page\u003c/a\u003e) to know more about how we collect, use and transfer the personal data of our candidates.\u003cbr/\u003e\u003cbr/\u003em/w/d\u003cbr/\u003e\u003cbr/\u003eOur inclusive culture empowers Amazonians to deliver the best results for our customers. If you have a disability and need a workplace accommodation or adjustment during the application and hiring process, including support for the interview or onboarding process, please visit \u003ca href=\"https://amazon.jobs/content/en/how-we-hire/accommodations\"\u003ehttps://amazon.jobs/content/en/how-we-hire/accommodations\u003c/a\u003e for more information. If the country/region you’re applying in isn’t listed, please contact your Recruiting Partner.","primary_search_label":"fulfillment-and-operations.team-last-mile-delivery","source_system":"JobCreator","state":"ST","title":"Graduate Logistik Manager - Straubing, Bayern","university_job":null,"updated_time":"20 minutes","url_next_step":"https://account.amazon.com/jobs/10394540/apply","team":{"id":null,"business_category_id":null,"identifier":null,"label":"team-last-mile-delivery","created_at":null,"updated_at":null,"image_file_name":null,"image_content_type":null,"image_file_size":null,"image_updated_at":null,"thumbnail_file_name":null,"thumbnail_content_type":null,"thumbnail_file_size":null,"thumbnail_updated_at":null,"hide_jobs":null,"title":null,"headline":null,"description":null}},{"basic_qualifications":"- 1+ years of Windows Server technologies: AD, DFS, Print Services, SCCM experience\u003cbr/\u003e- 2+ years of troubleshooting in a multi-user high availability environment experience\u003cbr/\u003e- 2+ years of PC repair, troubleshooting, deployment and liquidation experience\u003cbr/\u003e- 1+ years of IT client, server, and network service delivery experience\u003cbr/\u003e- 2+ years of networking (such as DNS, DHCP, SSL, OSI Model, and TCP/IP) experience\u003cbr/\u003e- 2+ years of corporate setting Windows, Mac or Linux Operating systems support experience\u003cbr/\u003e- 2+ years of supporting and maintaining a corporate network environment experience\u003cbr/\u003e- High school or equivalent diploma","business_category":"fulfillment-ops","city":"Virtual","company_name":"ADCI - Maharashtra","country_code":"IND","description":"Operations is at the heart of Amazon’s business. We are known for our speed, accuracy, and exceptional service. Our buildings deliver tens of thousands of products to hundreds of countries worldwide, every day. OTS provides nonstop global IT support to Amazon Operations as a vital piece to the puzzle. We are looking for self-motivated individuals to take on new challenges and motivate teams in fostering solutions to the hurdles we face. Together, we take ownership for what we do — whether supporting IT infrastructure, developing new technology in-house, launching a new Amazon Operations facility, or delighting our customers by delivering packages directly to them.\u003cbr/\u003e\u003cbr/\u003eAbout The Role\u003cbr/\u003eAs an IT Support Engineer I, you will use your knowledge and specialized skills to implement technical solutions and provide high quality support for computer hardware, operating systems, or enterprise application software across sites in a defined geographical area. You are able to determine when it is appropriate to deviate from a standard practice to accomplish the desired result. You can troubleshoot and solve straightforward problems that do not have defined SOPs.\u003cbr/\u003e\u003cbr/\u003e\u003cbr/\u003eKey job responsibilities\u003cbr/\u003eManaging local technical projects.\u003cbr/\u003eMaintaining or creating policies, procedures, and processes.\u003cbr/\u003eIdentifying root-causes of operational issues and process inefficiencies.\u003cbr/\u003eSupporting global customers remotely.\u003cbr/\u003eTraveling within your local or regional area to support our customers.","department_cost_center":null,"description_short":"Operations is at the heart of Amazon’s business. We are known for our speed, accuracy, and exceptional service. Our buildings deliver tens of thousands of products to hundreds of countries worldwide, every","display_distance":null,"id":"c94da966-c1b6-45b2-aded-5a5d1d482d03","id_icims":"3204738","is_intern":null,"is_manager":null,"job_category":"Operations, IT, \u0026 Support Engineering","job_family":"Technical Services","job_function_id":null,"job_path":"/en/jobs/3204738/it-support-engineer-i-ops-tech-solutions-delivery","job_schedule_type":"full-time","location":"IN, MH, Virtual","locations":["{\"normalizedStateName\":\"Karnataka\",\"normalizedCountryCode\":\"IND\",\"city\":\"Bangalore - Virtual\",\"countryIso3a\":\"IND\",\"countryIso2a\":\"IN\",\"locationNonStemming\":\"India, KA, Bangalore - Virtual\",\"coordinates\":\"12.96617,77.58692\",\"normalizedCountyName\":\"Bengaluru\",\"type\":\"VIRTUAL\",\"normalizedCountryName\":\"India\",\"normalizedLocation\":\"Bengaluru, Karnataka, IND\",\"location\":\"IN, KA, Bangalore - Virtual\",\"region\":\"KA\",\"buildingCodeList\":[\"VCCKA1IN\"],\"normalizedCityName\":\"Bengaluru\"}","{\"normalizedStateName\":\"Maharashtra\",\"normalizedCountryCode\":\"IND\",\"city\":\"Virtual\",\"countryIso3a\":\"IND\",\"countryIso2a\":\"IN\",\"locationNonStemming\":\"India, MH, Virtual\",\"coordinates\":\"18.94018,72.83484\",\"type\":\"VIRTUAL\",\"normalizedCountryName\":\"India\",\"normalizedLocation\":\"Maharashtra, IND\",\"location\":\"IN, MH, Virtual\",\"region\":\"MH\",\"buildingCodeList\":[\"VCC25\"]}"],"normalized_location":"Maharashtra, IND","optional_search_labels":["amazon-india-operations"],"posted_date":"March 13, 2026","preferred_qualifications":"- 2+ years of computer networking experience\u003cbr/\u003e- Experience supporting video conference and teleconference equipment\u003cbr/\u003e\u003cbr/\u003eOur inclusive culture empowers Amazonians to deliver the best results for our customers. If you have a disability and need a workplace accommodation or adjustment during the application and hiring process, including support for the interview or onboarding process, please visit \u003ca href=\"https://amazon.jobs/content/en/how-we-hire/accommodations\"\u003ehttps://amazon.jobs/content/en/how-we-hire/accommodations\u003c/a\u003e for more information. If the country/region you’re applying in isn’t listed, please contact your Recruiting Partner.","primary_search_label":"fulfillment-ops.team-engineering-it","source_system":"JobCreator","state":"MH","title":"IT Support Engineer I, Ops Tech Solutions Delivery","university_job":null,"updated_time":"23 minutes","url_next_step":"https://account.amazon.com/jobs/3204738/apply","team":{"id":null,"business_category_id":null,"identifier":null,"label":"team-engineering-it","created_at":null,"updated_at":null,"image_file_name":null,"image_content_type":null,"image_file_size":null,"image_updated_at":null,"thumbnail_file_name":null,"thumbnail_content_type":null,"thumbnail_file_size":null,"thumbnail_updated_at":null,"hide_jobs":null,"title":null,"headline":null,"description":null}}],"job_posting_search_request":"{\"jobPostingSearchRequest\":{\"query\":\"\",\"excludeFacets\":[{\"name\":\"businessCategory\",\"values\":[{\"name\":\"a-confidential-job\"}]},{\"name\":\"isPostedExternally\",\"values\":[{\"name\":\"0\"}]},{\"name\":\"isUnsearchable\",\"values\":[{\"name\":\"1\"}]}],\"filterFacets\":[],\"start\":0,\"size\":10,\"sort\":{\"sortOrder\":\"DESCENDING\",\"sortType\":\"SCORE\"},\"location\":null,\"accessLevel\":\"EXTERNAL\",\"includeFacets\":[],\"locationFacets\":[],\"jobTypeFacets\":[],\"contentFilterFacets\":[],\"treatment\":\"OM\"}}"}